{
  "id": "557cdc4c-a0d7-401f-a19f-75bb504d17b2",
  "prevId": "00000000-0000-0000-0000-000000000000",
  "version": "7",
  "dialect": "postgresql",
  "tables": {
    "public.ai_prompts": {
      "name": "ai_prompts",
      "schema": "",
      "columns": {
        "id": {
          "name": "id",
          "type": "uuid",
          "primaryKey": true,
          "notNull": true,
          "default": "gen_random_uuid()"
        },
        "created_at": {
          "name": "created_at",
          "type": "timestamp with time zone",
          "primaryKey": false,
          "notNull": false,
          "default": "now()"
        },
        "updated_at": {
          "name": "updated_at",
          "type": "timestamp with time zone",
          "primaryKey": false,
          "notNull": false,
          "default": "now()"
        },
        "name": {
          "name": "name",
          "type": "text",
          "primaryKey": false,
          "notNull": true
        },
        "prompt_text": {
          "name": "prompt_text",
          "type": "text",
          "primaryKey": false,
          "notNull": true
        },
        "is_active": {
          "name": "is_active",
          "type": "boolean",
          "primaryKey": false,
          "notNull": true,
          "default": true
        },
        "category": {
          "name": "category",
          "type": "text",
          "primaryKey": false,
          "notNull": false,
          "default": "'booking_reply'"
        }
      },
      "indexes": {},
      "foreignKeys": {},
      "compositePrimaryKeys": {},
      "uniqueConstraints": {},
      "policies": {},
      "checkConstraints": {},
      "isRLSEnabled": false
    },
    "public.body_part_mappings": {
      "name": "body_part_mappings",
      "schema": "",
      "columns": {
        "id": {
          "name": "id",
          "type": "uuid",
          "primaryKey": true,
          "notNull": true,
          "default": "gen_random_uuid()"
        },
        "created_at": {
          "name": "created_at",
          "type": "timestamp with time zone",
          "primaryKey": false,
          "notNull": false,
          "default": "now()"
        },
        "updated_at": {
          "name": "updated_at",
          "type": "timestamp with time zone",
          "primaryKey": false,
          "notNull": false,
          "default": "now()"
        },
        "category": {
          "name": "category",
          "type": "text",
          "primaryKey": false,
          "notNull": true
        },
        "placement": {
          "name": "placement",
          "type": "text",
          "primaryKey": false,
          "notNull": true
        },
        "position_x": {
          "name": "position_x",
          "type": "real",
          "primaryKey": false,
          "notNull": true
        },
        "position_y": {
          "name": "position_y",
          "type": "real",
          "primaryKey": false,
          "notNull": true
        },
        "position_z": {
          "name": "position_z",
          "type": "real",
          "primaryKey": false,
          "notNull": true
        },
        "scale": {
          "name": "scale",
          "type": "real",
          "primaryKey": false,
          "notNull": true,
          "default": 1
        },
        "camera_azimuth": {
          "name": "camera_azimuth",
          "type": "real",
          "primaryKey": false,
          "notNull": false
        },
        "camera_polar": {
          "name": "camera_polar",
          "type": "real",
          "primaryKey": false,
          "notNull": false
        },
        "camera_distance": {
          "name": "camera_distance",
          "type": "real",
          "primaryKey": false,
          "notNull": false
        },
        "size_limit_min": {
          "name": "size_limit_min",
          "type": "real",
          "primaryKey": false,
          "notNull": false
        },
        "size_limit_max": {
          "name": "size_limit_max",
          "type": "real",
          "primaryKey": false,
          "notNull": false
        },
        "size_limit_multiplier": {
          "name": "size_limit_multiplier",
          "type": "real",
          "primaryKey": false,
          "notNull": false
        },
        "pain_level": {
          "name": "pain_level",
          "type": "real",
          "primaryKey": false,
          "notNull": false
        },
        "pain_reason": {
          "name": "pain_reason",
          "type": "text",
          "primaryKey": false,
          "notNull": false
        },
        "is_active": {
          "name": "is_active",
          "type": "boolean",
          "primaryKey": false,
          "notNull": true,
          "default": true
        }
      },
      "indexes": {},
      "foreignKeys": {},
      "compositePrimaryKeys": {},
      "uniqueConstraints": {},
      "policies": {},
      "checkConstraints": {},
      "isRLSEnabled": false
    },
    "public.bookings": {
      "name": "bookings",
      "schema": "",
      "columns": {
        "id": {
          "name": "id",
          "type": "uuid",
          "primaryKey": true,
          "notNull": true,
          "default": "gen_random_uuid()"
        },
        "created_at": {
          "name": "created_at",
          "type": "timestamp with time zone",
          "primaryKey": false,
          "notNull": true,
          "default": "now()"
        },
        "updated_at": {
          "name": "updated_at",
          "type": "timestamp with time zone",
          "primaryKey": false,
          "notNull": true,
          "default": "now()"
        },
        "status": {
          "name": "status",
          "type": "booking_status",
          "typeSchema": "public",
          "primaryKey": false,
          "notNull": true,
          "default": "'Pending'"
        },
        "name": {
          "name": "name",
          "type": "text",
          "primaryKey": false,
          "notNull": true
        },
        "email": {
          "name": "email",
          "type": "text",
          "primaryKey": false,
          "notNull": true
        },
        "phone": {
          "name": "phone",
          "type": "text",
          "primaryKey": false,
          "notNull": true
        },
        "dob": {
          "name": "dob",
          "type": "text",
          "primaryKey": false,
          "notNull": false
        },
        "instagram_handle": {
          "name": "instagram_handle",
          "type": "text",
          "primaryKey": false,
          "notNull": false
        },
        "facebook_profile": {
          "name": "facebook_profile",
          "type": "text",
          "primaryKey": false,
          "notNull": false
        },
        "preferred_contact": {
          "name": "preferred_contact",
          "type": "text",
          "primaryKey": false,
          "notNull": false
        },
        "referral_source": {
          "name": "referral_source",
          "type": "text",
          "primaryKey": false,
          "notNull": false
        },
        "tattoo_size": {
          "name": "tattoo_size",
          "type": "real",
          "primaryKey": false,
          "notNull": true
        },
        "is_color": {
          "name": "is_color",
          "type": "boolean",
          "primaryKey": false,
          "notNull": true,
          "default": false
        },
        "complexity": {
          "name": "complexity",
          "type": "real",
          "primaryKey": false,
          "notNull": false
        },
        "category": {
          "name": "category",
          "type": "text",
          "primaryKey": false,
          "notNull": false
        },
        "placement": {
          "name": "placement",
          "type": "text",
          "primaryKey": false,
          "notNull": false
        },
        "placement_index": {
          "name": "placement_index",
          "type": "integer",
          "primaryKey": false,
          "notNull": false,
          "default": 0
        },
        "is_cover_up": {
          "name": "is_cover_up",
          "type": "boolean",
          "primaryKey": false,
          "notNull": true,
          "default": false
        },
        "primary_tattoo_style": {
          "name": "primary_tattoo_style",
          "type": "text",
          "primaryKey": false,
          "notNull": false
        },
        "style_description": {
          "name": "style_description",
          "type": "text",
          "primaryKey": false,
          "notNull": false
        },
        "pricing_details": {
          "name": "pricing_details",
          "type": "jsonb",
          "primaryKey": false,
          "notNull": false
        },
        "estimated_duration": {
          "name": "estimated_duration",
          "type": "integer",
          "primaryKey": false,
          "notNull": false
        },
        "estimated_sessions": {
          "name": "estimated_sessions",
          "type": "integer",
          "primaryKey": false,
          "notNull": false
        },
        "reference_image_urls": {
          "name": "reference_image_urls",
          "type": "jsonb",
          "primaryKey": false,
          "notNull": false
        },
        "creative_freedom": {
          "name": "creative_freedom",
          "type": "real",
          "primaryKey": false,
          "notNull": true,
          "default": 50
        },
        "specific_reqs": {
          "name": "specific_reqs",
          "type": "text",
          "primaryKey": false,
          "notNull": false
        },
        "must_haves": {
          "name": "must_haves",
          "type": "text",
          "primaryKey": false,
          "notNull": false
        },
        "color_prefs": {
          "name": "color_prefs",
          "type": "text",
          "primaryKey": false,
          "notNull": false
        },
        "placement_notes": {
          "name": "placement_notes",
          "type": "text",
          "primaryKey": false,
          "notNull": false
        },
        "requested_date": {
          "name": "requested_date",
          "type": "text",
          "primaryKey": false,
          "notNull": false
        },
        "requested_time": {
          "name": "requested_time",
          "type": "text",
          "primaryKey": false,
          "notNull": false
        },
        "artist_preference": {
          "name": "artist_preference",
          "type": "text",
          "primaryKey": false,
          "notNull": false
        },
        "urgency_level": {
          "name": "urgency_level",
          "type": "text",
          "primaryKey": false,
          "notNull": false
        },
        "terms_agreed": {
          "name": "terms_agreed",
          "type": "boolean",
          "primaryKey": false,
          "notNull": false,
          "default": false
        },
        "medical_confirmed": {
          "name": "medical_confirmed",
          "type": "boolean",
          "primaryKey": false,
          "notNull": false,
          "default": false
        },
        "age_confirmed": {
          "name": "age_confirmed",
          "type": "boolean",
          "primaryKey": false,
          "notNull": false,
          "default": false
        },
        "pain_level": {
          "name": "pain_level",
          "type": "real",
          "primaryKey": false,
          "notNull": false
        },
        "pain_reason": {
          "name": "pain_reason",
          "type": "text",
          "primaryKey": false,
          "notNull": false
        },
        "visual_complexity_score": {
          "name": "visual_complexity_score",
          "type": "real",
          "primaryKey": false,
          "notNull": false
        },
        "admin_notes": {
          "name": "admin_notes",
          "type": "text",
          "primaryKey": false,
          "notNull": false
        },
        "saved_reply_recommendations": {
          "name": "saved_reply_recommendations",
          "type": "jsonb",
          "primaryKey": false,
          "notNull": false
        }
      },
      "indexes": {},
      "foreignKeys": {},
      "compositePrimaryKeys": {},
      "uniqueConstraints": {},
      "policies": {},
      "checkConstraints": {},
      "isRLSEnabled": false
    },
    "public.kpi_activity_log": {
      "name": "kpi_activity_log",
      "schema": "",
      "columns": {
        "id": {
          "name": "id",
          "type": "uuid",
          "primaryKey": true,
          "notNull": true,
          "default": "gen_random_uuid()"
        },
        "created_at": {
          "name": "created_at",
          "type": "timestamp with time zone",
          "primaryKey": false,
          "notNull": true,
          "default": "now()"
        },
        "business": {
          "name": "business",
          "type": "marketing_business",
          "typeSchema": "public",
          "primaryKey": false,
          "notNull": true
        },
        "category": {
          "name": "category",
          "type": "text",
          "primaryKey": false,
          "notNull": true
        },
        "action": {
          "name": "action",
          "type": "text",
          "primaryKey": false,
          "notNull": true
        },
        "value": {
          "name": "value",
          "type": "real",
          "primaryKey": false,
          "notNull": false,
          "default": 1
        },
        "metadata": {
          "name": "metadata",
          "type": "jsonb",
          "primaryKey": false,
          "notNull": false
        },
        "notes": {
          "name": "notes",
          "type": "text",
          "primaryKey": false,
          "notNull": false
        }
      },
      "indexes": {},
      "foreignKeys": {},
      "compositePrimaryKeys": {},
      "uniqueConstraints": {},
      "policies": {},
      "checkConstraints": {},
      "isRLSEnabled": false
    },
    "public.leads": {
      "name": "leads",
      "schema": "",
      "columns": {
        "id": {
          "name": "id",
          "type": "uuid",
          "primaryKey": true,
          "notNull": true,
          "default": "gen_random_uuid()"
        },
        "created_at": {
          "name": "created_at",
          "type": "timestamp with time zone",
          "primaryKey": false,
          "notNull": true,
          "default": "now()"
        },
        "updated_at": {
          "name": "updated_at",
          "type": "timestamp with time zone",
          "primaryKey": false,
          "notNull": true,
          "default": "now()"
        },
        "business": {
          "name": "business",
          "type": "marketing_business",
          "typeSchema": "public",
          "primaryKey": false,
          "notNull": true
        },
        "status": {
          "name": "status",
          "type": "lead_status",
          "typeSchema": "public",
          "primaryKey": false,
          "notNull": true,
          "default": "'new'"
        },
        "source": {
          "name": "source",
          "type": "lead_source",
          "typeSchema": "public",
          "primaryKey": false,
          "notNull": true,
          "default": "'other'"
        },
        "name": {
          "name": "name",
          "type": "text",
          "primaryKey": false,
          "notNull": true
        },
        "phone": {
          "name": "phone",
          "type": "text",
          "primaryKey": false,
          "notNull": false
        },
        "email": {
          "name": "email",
          "type": "text",
          "primaryKey": false,
          "notNull": false
        },
        "facebook": {
          "name": "facebook",
          "type": "text",
          "primaryKey": false,
          "notNull": false
        },
        "instagram": {
          "name": "instagram",
          "type": "text",
          "primaryKey": false,
          "notNull": false
        },
        "interest": {
          "name": "interest",
          "type": "text",
          "primaryKey": false,
          "notNull": false
        },
        "estimated_value": {
          "name": "estimated_value",
          "type": "real",
          "primaryKey": false,
          "notNull": false
        },
        "notes": {
          "name": "notes",
          "type": "text",
          "primaryKey": false,
          "notNull": false
        },
        "last_contacted_at": {
          "name": "last_contacted_at",
          "type": "timestamp with time zone",
          "primaryKey": false,
          "notNull": false
        },
        "next_follow_up_at": {
          "name": "next_follow_up_at",
          "type": "timestamp with time zone",
          "primaryKey": false,
          "notNull": false
        },
        "dms_sent": {
          "name": "dms_sent",
          "type": "integer",
          "primaryKey": false,
          "notNull": true,
          "default": 0
        },
        "dms_received": {
          "name": "dms_received",
          "type": "integer",
          "primaryKey": false,
          "notNull": true,
          "default": 0
        },
        "calls_made": {
          "name": "calls_made",
          "type": "integer",
          "primaryKey": false,
          "notNull": true,
          "default": 0
        },
        "converted_at": {
          "name": "converted_at",
          "type": "timestamp with time zone",
          "primaryKey": false,
          "notNull": false
        },
        "converted_value": {
          "name": "converted_value",
          "type": "real",
          "primaryKey": false,
          "notNull": false
        },
        "lost_reason": {
          "name": "lost_reason",
          "type": "text",
          "primaryKey": false,
          "notNull": false
        }
      },
      "indexes": {},
      "foreignKeys": {},
      "compositePrimaryKeys": {},
      "uniqueConstraints": {},
      "policies": {},
      "checkConstraints": {},
      "isRLSEnabled": false
    },
    "public.marketing_calendar": {
      "name": "marketing_calendar",
      "schema": "",
      "columns": {
        "id": {
          "name": "id",
          "type": "uuid",
          "primaryKey": true,
          "notNull": true,
          "default": "gen_random_uuid()"
        },
        "created_at": {
          "name": "created_at",
          "type": "timestamp with time zone",
          "primaryKey": false,
          "notNull": true,
          "default": "now()"
        },
        "business": {
          "name": "business",
          "type": "marketing_business",
          "typeSchema": "public",
          "primaryKey": false,
          "notNull": true
        },
        "date": {
          "name": "date",
          "type": "text",
          "primaryKey": false,
          "notNull": true
        },
        "day_of_week": {
          "name": "day_of_week",
          "type": "text",
          "primaryKey": false,
          "notNull": true
        },
        "theme": {
          "name": "theme",
          "type": "text",
          "primaryKey": false,
          "notNull": false
        },
        "content_ids": {
          "name": "content_ids",
          "type": "jsonb",
          "primaryKey": false,
          "notNull": false
        },
        "notes": {
          "name": "notes",
          "type": "text",
          "primaryKey": false,
          "notNull": false
        }
      },
      "indexes": {},
      "foreignKeys": {},
      "compositePrimaryKeys": {},
      "uniqueConstraints": {},
      "policies": {},
      "checkConstraints": {},
      "isRLSEnabled": false
    },
    "public.marketing_content": {
      "name": "marketing_content",
      "schema": "",
      "columns": {
        "id": {
          "name": "id",
          "type": "uuid",
          "primaryKey": true,
          "notNull": true,
          "default": "gen_random_uuid()"
        },
        "created_at": {
          "name": "created_at",
          "type": "timestamp with time zone",
          "primaryKey": false,
          "notNull": true,
          "default": "now()"
        },
        "updated_at": {
          "name": "updated_at",
          "type": "timestamp with time zone",
          "primaryKey": false,
          "notNull": true,
          "default": "now()"
        },
        "business": {
          "name": "business",
          "type": "marketing_business",
          "typeSchema": "public",
          "primaryKey": false,
          "notNull": true
        },
        "content_type": {
          "name": "content_type",
          "type": "content_type",
          "typeSchema": "public",
          "primaryKey": false,
          "notNull": true
        },
        "platform": {
          "name": "platform",
          "type": "platform_type",
          "typeSchema": "public",
          "primaryKey": false,
          "notNull": true
        },
        "pipeline_stage": {
          "name": "pipeline_stage",
          "type": "pipeline_stage",
          "typeSchema": "public",
          "primaryKey": false,
          "notNull": true
        },
        "status": {
          "name": "status",
          "type": "content_status",
          "typeSchema": "public",
          "primaryKey": false,
          "notNull": true,
          "default": "'draft'"
        },
        "title": {
          "name": "title",
          "type": "text",
          "primaryKey": false,
          "notNull": true
        },
        "caption": {
          "name": "caption",
          "type": "text",
          "primaryKey": false,
          "notNull": false
        },
        "image_url": {
          "name": "image_url",
          "type": "text",
          "primaryKey": false,
          "notNull": false
        },
        "image_prompt": {
          "name": "image_prompt",
          "type": "text",
          "primaryKey": false,
          "notNull": false
        },
        "hashtags": {
          "name": "hashtags",
          "type": "jsonb",
          "primaryKey": false,
          "notNull": false
        },
        "scheduled_at": {
          "name": "scheduled_at",
          "type": "timestamp with time zone",
          "primaryKey": false,
          "notNull": false
        },
        "published_at": {
          "name": "published_at",
          "type": "timestamp with time zone",
          "primaryKey": false,
          "notNull": false
        },
        "ai_model": {
          "name": "ai_model",
          "type": "text",
          "primaryKey": false,
          "notNull": false
        },
        "ai_prompt_used": {
          "name": "ai_prompt_used",
          "type": "text",
          "primaryKey": false,
          "notNull": false
        },
        "generation_cost": {
          "name": "generation_cost",
          "type": "real",
          "primaryKey": false,
          "notNull": false
        },
        "reach": {
          "name": "reach",
          "type": "integer",
          "primaryKey": false,
          "notNull": false
        },
        "engagement": {
          "name": "engagement",
          "type": "integer",
          "primaryKey": false,
          "notNull": false
        },
        "clicks": {
          "name": "clicks",
          "type": "integer",
          "primaryKey": false,
          "notNull": false
        },
        "shares": {
          "name": "shares",
          "type": "integer",
          "primaryKey": false,
          "notNull": false
        },
        "notes": {
          "name": "notes",
          "type": "text",
          "primaryKey": false,
          "notNull": false
        },
        "approved_by": {
          "name": "approved_by",
          "type": "text",
          "primaryKey": false,
          "notNull": false
        }
      },
      "indexes": {},
      "foreignKeys": {},
      "compositePrimaryKeys": {},
      "uniqueConstraints": {},
      "policies": {},
      "checkConstraints": {},
      "isRLSEnabled": false
    },
    "public.marketing_templates": {
      "name": "marketing_templates",
      "schema": "",
      "columns": {
        "id": {
          "name": "id",
          "type": "uuid",
          "primaryKey": true,
          "notNull": true,
          "default": "gen_random_uuid()"
        },
        "created_at": {
          "name": "created_at",
          "type": "timestamp with time zone",
          "primaryKey": false,
          "notNull": true,
          "default": "now()"
        },
        "business": {
          "name": "business",
          "type": "marketing_business",
          "typeSchema": "public",
          "primaryKey": false,
          "notNull": true
        },
        "content_type": {
          "name": "content_type",
          "type": "content_type",
          "typeSchema": "public",
          "primaryKey": false,
          "notNull": true
        },
        "name": {
          "name": "name",
          "type": "text",
          "primaryKey": false,
          "notNull": true
        },
        "prompt_template": {
          "name": "prompt_template",
          "type": "text",
          "primaryKey": false,
          "notNull": true
        },
        "caption_template": {
          "name": "caption_template",
          "type": "text",
          "primaryKey": false,
          "notNull": false
        },
        "platform": {
          "name": "platform",
          "type": "platform_type",
          "typeSchema": "public",
          "primaryKey": false,
          "notNull": true
        },
        "pipeline_stage": {
          "name": "pipeline_stage",
          "type": "pipeline_stage",
          "typeSchema": "public",
          "primaryKey": false,
          "notNull": true
        },
        "is_active": {
          "name": "is_active",
          "type": "boolean",
          "primaryKey": false,
          "notNull": true,
          "default": true
        },
        "variables": {
          "name": "variables",
          "type": "jsonb",
          "primaryKey": false,
          "notNull": false
        }
      },
      "indexes": {},
      "foreignKeys": {},
      "compositePrimaryKeys": {},
      "uniqueConstraints": {},
      "policies": {},
      "checkConstraints": {},
      "isRLSEnabled": false
    },
    "public.media_assets": {
      "name": "media_assets",
      "schema": "",
      "columns": {
        "id": {
          "name": "id",
          "type": "uuid",
          "primaryKey": true,
          "notNull": true,
          "default": "gen_random_uuid()"
        },
        "created_at": {
          "name": "created_at",
          "type": "timestamp with time zone",
          "primaryKey": false,
          "notNull": true,
          "default": "now()"
        },
        "updated_at": {
          "name": "updated_at",
          "type": "timestamp with time zone",
          "primaryKey": false,
          "notNull": true,
          "default": "now()"
        },
        "key": {
          "name": "key",
          "type": "text",
          "primaryKey": false,
          "notNull": true
        },
        "url": {
          "name": "url",
          "type": "text",
          "primaryKey": false,
          "notNull": true
        },
        "original_filename": {
          "name": "original_filename",
          "type": "text",
          "primaryKey": false,
          "notNull": true
        },
        "mime_type": {
          "name": "mime_type",
          "type": "text",
          "primaryKey": false,
          "notNull": true
        },
        "size_bytes": {
          "name": "size_bytes",
          "type": "integer",
          "primaryKey": false,
          "notNull": false
        },
        "category": {
          "name": "category",
          "type": "asset_category",
          "typeSchema": "public",
          "primaryKey": false,
          "notNull": true,
          "default": "'misc'"
        },
        "title": {
          "name": "title",
          "type": "text",
          "primaryKey": false,
          "notNull": false
        },
        "alt_text": {
          "name": "alt_text",
          "type": "text",
          "primaryKey": false,
          "notNull": false
        },
        "tags": {
          "name": "tags",
          "type": "jsonb",
          "primaryKey": false,
          "notNull": false
        },
        "width": {
          "name": "width",
          "type": "integer",
          "primaryKey": false,
          "notNull": false
        },
        "height": {
          "name": "height",
          "type": "integer",
          "primaryKey": false,
          "notNull": false
        },
        "is_public": {
          "name": "is_public",
          "type": "boolean",
          "primaryKey": false,
          "notNull": true,
          "default": true
        },
        "display_order": {
          "name": "display_order",
          "type": "integer",
          "primaryKey": false,
          "notNull": false,
          "default": 0
        }
      },
      "indexes": {},
      "foreignKeys": {},
      "compositePrimaryKeys": {},
      "uniqueConstraints": {
        "media_assets_key_unique": {
          "name": "media_assets_key_unique",
          "nullsNotDistinct": false,
          "columns": [
            "key"
          ]
        }
      },
      "policies": {},
      "checkConstraints": {},
      "isRLSEnabled": false
    },
    "public.portfolio_items": {
      "name": "portfolio_items",
      "schema": "",
      "columns": {
        "id": {
          "name": "id",
          "type": "uuid",
          "primaryKey": true,
          "notNull": true,
          "default": "gen_random_uuid()"
        },
        "created_at": {
          "name": "created_at",
          "type": "timestamp with time zone",
          "primaryKey": false,
          "notNull": false,
          "default": "now()"
        },
        "type": {
          "name": "type",
          "type": "text",
          "primaryKey": false,
          "notNull": true
        },
        "title": {
          "name": "title",
          "type": "text",
          "primaryKey": false,
          "notNull": true
        },
        "description": {
          "name": "description",
          "type": "text",
          "primaryKey": false,
          "notNull": false
        },
        "image_url": {
          "name": "image_url",
          "type": "text",
          "primaryKey": false,
          "notNull": false
        },
        "tags": {
          "name": "tags",
          "type": "jsonb",
          "primaryKey": false,
          "notNull": false
        },
        "slug": {
          "name": "slug",
          "type": "text",
          "primaryKey": false,
          "notNull": false
        },
        "tech_stack": {
          "name": "tech_stack",
          "type": "jsonb",
          "primaryKey": false,
          "notNull": false
        },
        "live_url": {
          "name": "live_url",
          "type": "text",
          "primaryKey": false,
          "notNull": false
        },
        "github_url": {
          "name": "github_url",
          "type": "text",
          "primaryKey": false,
          "notNull": false
        },
        "case_study_content": {
          "name": "case_study_content",
          "type": "text",
          "primaryKey": false,
          "notNull": false
        },
        "style": {
          "name": "style",
          "type": "text",
          "primaryKey": false,
          "notNull": false
        },
        "placement": {
          "name": "placement",
          "type": "text",
          "primaryKey": false,
          "notNull": false
        },
        "is_published": {
          "name": "is_published",
          "type": "boolean",
          "primaryKey": false,
          "notNull": true,
          "default": true
        },
        "display_order": {
          "name": "display_order",
          "type": "integer",
          "primaryKey": false,
          "notNull": false,
          "default": 0
        }
      },
      "indexes": {},
      "foreignKeys": {},
      "compositePrimaryKeys": {},
      "uniqueConstraints": {
        "portfolio_items_slug_unique": {
          "name": "portfolio_items_slug_unique",
          "nullsNotDistinct": false,
          "columns": [
            "slug"
          ]
        }
      },
      "policies": {},
      "checkConstraints": {},
      "isRLSEnabled": false
    },
    "public.scheduling_slots": {
      "name": "scheduling_slots",
      "schema": "",
      "columns": {
        "id": {
          "name": "id",
          "type": "uuid",
          "primaryKey": true,
          "notNull": true,
          "default": "gen_random_uuid()"
        },
        "date": {
          "name": "date",
          "type": "text",
          "primaryKey": false,
          "notNull": true
        },
        "time": {
          "name": "time",
          "type": "text",
          "primaryKey": false,
          "notNull": true
        },
        "is_available": {
          "name": "is_available",
          "type": "boolean",
          "primaryKey": false,
          "notNull": true,
          "default": true
        },
        "booking_id": {
          "name": "booking_id",
          "type": "uuid",
          "primaryKey": false,
          "notNull": false
        },
        "duration_minutes": {
          "name": "duration_minutes",
          "type": "integer",
          "primaryKey": false,
          "notNull": false,
          "default": 60
        }
      },
      "indexes": {},
      "foreignKeys": {
        "scheduling_slots_booking_id_bookings_id_fk": {
          "name": "scheduling_slots_booking_id_bookings_id_fk",
          "tableFrom": "scheduling_slots",
          "tableTo": "bookings",
          "columnsFrom": [
            "booking_id"
          ],
          "columnsTo": [
            "id"
          ],
          "onDelete": "set null",
          "onUpdate": "no action"
        }
      },
      "compositePrimaryKeys": {},
      "uniqueConstraints": {},
      "policies": {},
      "checkConstraints": {},
      "isRLSEnabled": false
    }
  },
  "enums": {
    "public.asset_category": {
      "name": "asset_category",
      "schema": "public",
      "values": [
        "tattoo",
        "painting",
        "flash",
        "design",
        "testimonial",
        "studio",
        "misc"
      ]
    },
    "public.booking_status": {
      "name": "booking_status",
      "schema": "public",
      "values": [
        "Available",
        "Pending",
        "Confirmed",
        "Rejected",
        "Completed",
        "Needs Info",
        "Conflict"
      ]
    },
    "public.content_status": {
      "name": "content_status",
      "schema": "public",
      "values": [
        "draft",
        "generated",
        "approved",
        "scheduled",
        "published",
        "failed"
      ]
    },
    "public.content_type": {
      "name": "content_type",
      "schema": "public",
      "values": [
        "menu_image",
        "promo_graphic",
        "social_caption",
        "story_post",
        "reel_script",
        "review_reply"
      ]
    },
    "public.lead_source": {
      "name": "lead_source",
      "schema": "public",
      "values": [
        "facebook",
        "instagram",
        "tiktok",
        "google",
        "walk_in",
        "referral",
        "dm",
        "email",
        "phone",
        "website",
        "other"
      ]
    },
    "public.lead_status": {
      "name": "lead_status",
      "schema": "public",
      "values": [
        "new",
        "contacted",
        "responded",
        "qualified",
        "proposal_sent",
        "negotiating",
        "won",
        "lost",
        "dormant"
      ]
    },
    "public.marketing_business": {
      "name": "marketing_business",
      "schema": "public",
      "values": [
        "silog",
        "sweetytreats",
        "foodhub",
        "dorm",
        "arjostyle"
      ]
    },
    "public.pipeline_stage": {
      "name": "pipeline_stage",
      "schema": "public",
      "values": [
        "awareness",
        "interest",
        "conversion",
        "retention",
        "advocacy"
      ]
    },
    "public.platform_type": {
      "name": "platform_type",
      "schema": "public",
      "values": [
        "facebook",
        "tiktok",
        "instagram",
        "google_business"
      ]
    }
  },
  "schemas": {},
  "sequences": {},
  "roles": {},
  "policies": {},
  "views": {},
  "_meta": {
    "columns": {},
    "schemas": {},
    "tables": {}
  }
}